{
  "I": "/acc/symbols/I.svg",
  "YOU": "/acc/symbols/you.svg",
  "ME": "/acc/symbols/me.svg",
  "GO": "/acc/symbols/go_,_to.svg",
  "STOP": "/acc/symbols/stop.svg",
  "LOOK": "/acc/symbols/look_,_to.svg",
  "SEE": "/acc/symbols/eyes.svg",
  "OPEN": "/acc/symbols/open.svg",
  "CLOSE": "/acc/symbols/close_,_to.svg",
  "EAT": "/acc/symbols/eat_,_to.svg",
  "DRINK": "/acc/symbols/drink.svg",
  "HELP": "/acc/symbols/help_,_to.svg",
  "WANT": "/acc/symbols/want_,_to.svg",
  "NEED": "/acc/symbols/need_toilet.svg",
  "COME": "/acc/symbols/come_,_to.svg",
  "LIKE": "/acc/symbols/like.svg",
  "PLAY": "/acc/symbols/play_,_to.svg",
  "FEEL": "/acc/symbols/feel.svg",
  "MORE": "/acc/symbols/more.svg",
  "BIG": "/acc/symbols/big_mac_switch.svg",
  "LITTLE": "/acc/symbols/little.svg",
  "GOOD": "/acc/symbols/good.svg",
  "BAD": "/acc/symbols/bad.svg",
  "HAPPY": "/acc/symbols/happy_lady.svg",
  "SAD": "/acc/symbols/sad_man.svg",
  "IN": "/acc/symbols/in.svg",
  "OUT": "/acc/symbols/out.svg",
  "UP": "/acc/symbols/up.svg",
  "DOWN": "/acc/symbols/down.svg",
  "ON": "/acc/symbols/on.svg",
  "OFF": "/acc/symbols/off.svg",
  "WHAT": "/acc/symbols/what.svg",
  "WHERE": "/acc/symbols/where_1.svg",
  "YES": "/acc/symbols/correct.svg",
  "NO": "/acc/symbols/mistake_no_wrong.svg",
  "PLEASE": "/acc/symbols/please.svg",
  "THANK YOU": "/acc/symbols/thank_you.svg",
  "ALL DONE": "/acc/symbols/finish.svg",
  "THIS": "/acc/symbols/pointed.svg",
  "THAT": "/acc/symbols/point_,_to.svg",
  "NOT": "/acc/symbols/not.svg",
  "NOW": "/acc/symbols/now.svg",
  "HERE": "/acc/symbols/here.svg"
}
